{
  "expense_information": [
    {
      "fund_name": "UTI Large & Mid Cap Fund Direct Growth",
      "source_url": "https://groww.in/mutual-funds/uti-large-mid-cap-fund-direct-growth",
      "chunk_type": "expense_information",
      "data": {
        "expense_ratio": "0.97%",
        "stamp_duty": "0.005%"
      }
    },
    {
      "fund_name": "UTI ELSS Tax Saver Fund Direct Growth",
      "source_url": "https://groww.in/mutual-funds/uti-long-term-equity-fund-tax-saving-direct-growth",
      "chunk_type": "expense_information",
      "data": {
        "expense_ratio": "0.91%",
        "stamp_duty": "0.005%"
      }
    },
    {
      "fund_name": "UTI Gold ETF FoF Direct Growth",
      "source_url": "https://groww.in/mutual-funds/uti-gold-etf-fof-direct-growth",
      "chunk_type": "expense_information",
      "data": {
        "expense_ratio": "0.18%",
        "stamp_duty": "0.005%"
      }
    },
    {
      "fund_name": "UTI Transportation and Logistics Fund Direct Growth",
      "source_url": "https://groww.in/mutual-funds/uti-transportation-and-logistics-fund-direct-growth",
      "chunk_type": "expense_information",
      "data": {
        "expense_ratio": "0.82%",
        "stamp_duty": "0.005%"
      }
    },
    {
      "fund_name": "UTI Healthcare Fund Direct Growth",
      "source_url": "https://groww.in/mutual-funds/uti-pharma-and-healthcare-fund-direct-growth",
      "chunk_type": "expense_information",
      "data": {
        "expense_ratio": "1.31%",
        "stamp_duty": "0.005%"
      }
    },
    {
      "fund_name": "UTI Small Cap Fund Direct Growth",
      "source_url": "https://groww.in/mutual-funds/uti-small-cap-fund-direct-growth",
      "chunk_type": "expense_information",
      "data": {
        "expense_ratio": "0.63%",
        "stamp_duty": "0.005%"
      }
    },
    {
      "fund_name": "UTI Value Fund Direct Growth",
      "source_url": "https://groww.in/mutual-funds/uti-value-fund-direct-growth",
      "chunk_type": "expense_information",
      "data": {
        "expense_ratio": "1.18%",
        "stamp_duty": "0.005%"
      }
    },
    {
      "fund_name": "UTI Mid Cap Fund Direct Growth",
      "source_url": "https://groww.in/mutual-funds/uti-mid-cap-fund-direct-growth",
      "chunk_type": "expense_information",
      "data": {
        "expense_ratio": "0.91%",
        "stamp_duty": "0.005%"
      }
    },
    {
      "fund_name": "UTI Nifty Next 50 Index Fund Direct Growth",
      "source_url": "https://groww.in/mutual-funds/uti-nifty-next-50-index-fund-direct-growth",
      "chunk_type": "expense_information",
      "data": {
        "expense_ratio": "0.34%",
        "stamp_duty": "0.005%"
      }
    },
    {
      "fund_name": "UTI Banking and Financial Services Fund Direct Plan Growth",
      "source_url": "https://groww.in/mutual-funds/uti-banking-sector-fund-direct-growth",
      "chunk_type": "expense_information",
      "data": {
        "expense_ratio": "1.11%",
        "stamp_duty": "0.005%"
      }
    },
    {
      "fund_name": "UTI Nifty 50 Index Fund Direct Growth",
      "source_url": "https://groww.in/mutual-funds/uti-nifty-fund-direct-growth",
      "chunk_type": "expense_information",
      "data": {
        "expense_ratio": "0.17%",
        "stamp_duty": "0.005%"
      }
    },
    {
      "fund_name": "UTI Flexi Cap Fund Direct Growth",
      "source_url": "https://groww.in/mutual-funds/uti-equity-fund-direct-growth",
      "chunk_type": "expense_information",
      "data": {
        "expense_ratio": "1.01%",
        "stamp_duty": "0.005%"
      }
    },
    {
      "fund_name": "UTI Money Market Fund Regular Plan Growth",
      "source_url": "https://groww.in/mutual-funds/uti-money-market-fund-regular-plan-growth",
      "chunk_type": "expense_information",
      "data": {
        "expense_ratio": "0.22%",
        "stamp_duty": "0.005%"
      }
    },
    {
      "fund_name": "UTI Liquid Direct Growth",
      "source_url": "https://groww.in/mutual-funds/uti-liquid-cash-plan-direct-growth",
      "chunk_type": "expense_information",
      "data": {
        "expense_ratio": "0.15%",
        "stamp_duty": "0.005%"
      }
    },
    {
      "fund_name": "UTI MNC Fund Direct Growth",
      "source_url": "https://groww.in/mutual-funds/uti-mnc-fund-direct-growth",
      "chunk_type": "expense_information",
      "data": {
        "expense_ratio": "1.25%",
        "stamp_duty": "0.005%"
      }
    },
    {
      "fund_name": "UTI India Consumer Fund Direct Growth",
      "source_url": "https://groww.in/mutual-funds/uti-india-lifestyle-fund-direct-growth",
      "chunk_type": "expense_information",
      "data": {
        "expense_ratio": "1.57%",
        "stamp_duty": "0.005%"
      }
    },
    {
      "fund_name": "UTI Long Term Advantage Fund Series III Direct Growth",
      "source_url": "https://groww.in/mutual-funds/uti-long-term-advantage-fund-series-iii-direct-growth",
      "chunk_type": "expense_information",
      "data": {
        "expense_ratio": "1.27%",
        "stamp_duty": "0.005%"
      }
    },
    {
      "fund_name": "UTI Healthcare Fund Direct IDCW",
      "source_url": "https://groww.in/mutual-funds/uti-pharma-and-healthcare-fund-direct-dividend",
      "chunk_type": "expense_information",
      "data": {
        "expense_ratio": "1.31%",
        "stamp_duty": "0.005%"
      }
    },
    {
      "fund_name": "UTI Income Plus Arbitrage Active FoF Direct Growth",
      "source_url": "https://groww.in/mutual-funds/uti-i-come-plus-arbitrage-active-fof-direct-growth",
      "chunk_type": "expense_information",
      "data": {
        "expense_ratio": "0.45%",
        "stamp_duty": "0.005%"
      }
    },
    {
      "fund_name": "UTI India Consumer Fund Direct IDCW",
      "source_url": "https://groww.in/mutual-funds/uti-india-lifestyle-fund-direct-dividend",
      "chunk_type": "expense_information",
      "data": {
        "expense_ratio": "1.57%",
        "stamp_duty": "0.005%"
      }
    },
    {
      "fund_name": "UTI Infrastructure Fund Direct Growth",
      "source_url": "https://groww.in/mutual-funds/uti-infrastructure-fund-direct-growth",
      "chunk_type": "expense_information",
      "data": {
        "expense_ratio": "1.35%",
        "stamp_duty": "0.005%"
      }
    },
    {
      "fund_name": "UTI Innovation Fund Direct Growth",
      "source_url": "https://groww.in/mutual-funds/uti-innovation-fund-direct-growth",
      "chunk_type": "expense_information",
      "data": {
        "expense_ratio": "1.42%",
        "stamp_duty": "0.005%"
      }
    },
    {
      "fund_name": "UTI Large & Mid Cap Fund Direct IDCW",
      "source_url": "https://groww.in/mutual-funds/uti-top-100-fund-direct-dividend",
      "chunk_type": "expense_information",
      "data": {
        "expense_ratio": "0.97%",
        "stamp_duty": "0.005%"
      }
    },
    {
      "fund_name": "UTI Large Cap Fund Direct Growth",
      "source_url": "https://groww.in/mutual-funds/uti-unit-scheme-1986-mastershare-direct-growth",
      "chunk_type": "expense_information",
      "data": {
        "expense_ratio": "0.72%",
        "stamp_duty": "0.005%"
      }
    },
    {
      "fund_name": "UTI Large Cap Fund Direct IDCW",
      "source_url": "https://groww.in/mutual-funds/uti-unit-scheme-1986-mastershare-direct-dividend",
      "chunk_type": "expense_information",
      "data": {
        "expense_ratio": "0.72%",
        "stamp_duty": "0.005%"
      }
    },
    {
      "fund_name": "UTI Liquid Cash Plan Direct IDCW Monthly",
      "source_url": "https://groww.in/mutual-funds/uti-liquid-cash-plan-direct-monthly-dividend",
      "chunk_type": "expense_information",
      "data": {
        "expense_ratio": "0.15%",
        "stamp_duty": "0.005%"
      }
    },
    {
      "fund_name": "UTI Long Duration Fund Direct IDCW Quarterly",
      "source_url": "https://groww.in/mutual-funds/uti-long-duration-fund-direct-idcw-quarterly",
      "chunk_type": "expense_information",
      "data": {
        "expense_ratio": "0.42%",
        "stamp_duty": "0.005%"
      }
    },
    {
      "fund_name": "UTI Long Term Advantage Fund Series V Direct Growth",
      "source_url": "https://groww.in/mutual-funds/uti-long-term-advantage-fund-series-v-direct-growth",
      "chunk_type": "expense_information",
      "data": {
        "expense_ratio": "1.27%",
        "stamp_duty": "0.005%"
      }
    },
    {
      "fund_name": "UTI Monthly Income Scheme Direct Growth",
      "source_url": "https://groww.in/mutual-funds/uti-monthly-i-come-scheme-direct-growth",
      "chunk_type": "expense_information",
      "data": {
        "expense_ratio": "0.68%",
        "stamp_duty": "0.005%"
      }
    },
    {
      "fund_name": "UTI Multi Asset Allocation Fund Direct Growth",
      "source_url": "https://groww.in/mutual-funds/uti-wealth-builder-fund-direct-growth",
      "chunk_type": "expense_information",
      "data": {
        "expense_ratio": "0.89%",
        "stamp_duty": "0.005%"
      }
    },
    {
      "fund_name": "UTI Multi Cap Fund (Ex) Direct Growth",
      "source_url": "https://groww.in/mutual-funds/uti-multi-cap-fund-%28ex%29-direct-growth",
      "chunk_type": "expense_information",
      "data": {
        "expense_ratio": "1.09%",
        "stamp_duty": "0.005%"
      }
    },
    {
      "fund_name": "UTI Multi Cap Fund Direct Growth",
      "source_url": "https://groww.in/mutual-funds/uti-multi-cap-fund-direct-growth",
      "chunk_type": "expense_information",
      "data": {
        "expense_ratio": "1.09%",
        "stamp_duty": "0.005%"
      }
    },
    {
      "fund_name": "UTI Nifty 500 Value 50 Index Fund Direct Growth",
      "source_url": "https://groww.in/mutual-funds/uti-nifty-500-value-50-index-fund-direct-growth",
      "chunk_type": "expense_information",
      "data": {
        "expense_ratio": "0.38%",
        "stamp_duty": "0.005%"
      }
    },
    {
      "fund_name": "UTI Nifty Alpha Low Volatility 30 Index Fund Direct Growth",
      "source_url": "https://groww.in/mutual-funds/uti-nifty-alpha-low-volatility-30-index-fund-direct-growth",
      "chunk_type": "expense_information",
      "data": {
        "expense_ratio": "0.41%",
        "stamp_duty": "0.005%"
      }
    },
    {
      "fund_name": "UTI Nifty India Manufacturing Index Fund Direct Growth",
      "source_url": "https://groww.in/mutual-funds/uti-nifty-india-manufacturing-index-fund-direct-growth",
      "chunk_type": "expense_information",
      "data": {
        "expense_ratio": "0.39%",
        "stamp_duty": "0.005%"
      }
    }
  ],
  "performance_metrics": [
    {
      "fund_name": "UTI Large & Mid Cap Fund Direct Growth",
      "source_url": "https://groww.in/mutual-funds/uti-large-mid-cap-fund-direct-growth",
      "chunk_type": "performance_metrics",
      "data": {
        "pe_ratio": 20.14,
        "pb_ratio": 3.03
      }
    },
    {
      "fund_name": "UTI ELSS Tax Saver Fund Direct Growth",
      "source_url": "https://groww.in/mutual-funds/uti-long-term-equity-fund-tax-saving-direct-growth",
      "chunk_type": "performance_metrics",
      "data": {
        "pe_ratio": 25.55,
        "pb_ratio": 3.79
      }
    },
    {
      "fund_name": "UTI Transportation and Logistics Fund Direct Growth",
      "source_url": "https://groww.in/mutual-funds/uti-transportation-and-logistics-fund-direct-growth",
      "chunk_type": "performance_metrics",
      "data": {
        "pe_ratio": 31.03,
        "pb_ratio": 5.58
      }
    },
    {
      "fund_name": "UTI Healthcare Fund Direct Growth",
      "source_url": "https://groww.in/mutual-funds/uti-pharma-and-healthcare-fund-direct-growth",
      "chunk_type": "performance_metrics",
      "data": {
        "pe_ratio": 39.36,
        "pb_ratio": 5.6
      }
    },
    {
      "fund_name": "UTI Small Cap Fund Direct Growth",
      "source_url": "https://groww.in/mutual-funds/uti-small-cap-fund-direct-growth",
      "chunk_type": "performance_metrics",
      "data": {
        "pe_ratio": 32.25,
        "pb_ratio": 4.33
      }
    },
    {
      "fund_name": "UTI Value Fund Direct Growth",
      "source_url": "https://groww.in/mutual-funds/uti-value-fund-direct-growth",
      "chunk_type": "performance_metrics",
      "data": {
        "pe_ratio": 22.14,
        "pb_ratio": 3.02
      }
    },
    {
      "fund_name": "UTI Mid Cap Fund Direct Growth",
      "source_url": "https://groww.in/mutual-funds/uti-mid-cap-fund-direct-growth",
      "chunk_type": "performance_metrics",
      "data": {
        "pe_ratio": 32.93,
        "pb_ratio": 4.83
      }
    },
    {
      "fund_name": "UTI Nifty Next 50 Index Fund Direct Growth",
      "source_url": "https://groww.in/mutual-funds/uti-nifty-next-50-index-fund-direct-growth",
      "chunk_type": "performance_metrics",
      "data": {
        "pe_ratio": 21.6,
        "pb_ratio": 3.68
      }
    },
    {
      "fund_name": "UTI Banking and Financial Services Fund Direct Plan Growth",
      "source_url": "https://groww.in/mutual-funds/uti-banking-sector-fund-direct-growth",
      "chunk_type": "performance_metrics",
      "data": {
        "pe_ratio": 19.02,
        "pb_ratio": 2.66
      }
    },
    {
      "fund_name": "UTI Nifty 50 Index Fund Direct Growth",
      "source_url": "https://groww.in/mutual-funds/uti-nifty-fund-direct-growth",
      "chunk_type": "performance_metrics",
      "data": {
        "pe_ratio": 24.11,
        "pb_ratio": 3.6
      }
    },
    {
      "fund_name": "UTI Flexi Cap Fund Direct Growth",
      "source_url": "https://groww.in/mutual-funds/uti-equity-fund-direct-growth",
      "chunk_type": "performance_metrics",
      "data": {
        "pe_ratio": 39.3,
        "pb_ratio": 6.04
      }
    },
    {
      "fund_name": "UTI MNC Fund Direct Growth",
      "source_url": "https://groww.in/mutual-funds/uti-mnc-fund-direct-growth",
      "chunk_type": "performance_metrics",
      "data": {
        "pe_ratio": 37.76,
        "pb_ratio": 6.93
      }
    },
    {
      "fund_name": "UTI India Consumer Fund Direct Growth",
      "source_url": "https://groww.in/mutual-funds/uti-india-lifestyle-fund-direct-growth",
      "chunk_type": "performance_metrics",
      "data": {
        "pe_ratio": 43.62,
        "pb_ratio": 8.08
      }
    },
    {
      "fund_name": "UTI Long Term Advantage Fund Series III Direct Growth",
      "source_url": "https://groww.in/mutual-funds/uti-long-term-advantage-fund-series-iii-direct-growth",
      "chunk_type": "performance_metrics",
      "data": {
        "pe_ratio": 29.01,
        "pb_ratio": 3.07
      }
    },
    {
      "fund_name": "UTI Healthcare Fund Direct IDCW",
      "source_url": "https://groww.in/mutual-funds/uti-pharma-and-healthcare-fund-direct-dividend",
      "chunk_type": "performance_metrics",
      "data": {
        "pe_ratio": 38.5,
        "pb_ratio": 5.4
      }
    },
    {
      "fund_name": "UTI Income Plus Arbitrage Active FoF Direct Growth",
      "source_url": "https://groww.in/mutual-funds/uti-i-come-plus-arbitrage-active-fof-direct-growth",
      "chunk_type": "performance_metrics",
      "data": {
        "pe_ratio": 18.2,
        "pb_ratio": 2.5
      }
    },
    {
      "fund_name": "UTI India Consumer Fund Direct IDCW",
      "source_url": "https://groww.in/mutual-funds/uti-india-lifestyle-fund-direct-dividend",
      "chunk_type": "performance_metrics",
      "data": {
        "pe_ratio": 42.8,
        "pb_ratio": 7.9
      }
    },
    {
      "fund_name": "UTI Infrastructure Fund Direct Growth",
      "source_url": "https://groww.in/mutual-funds/uti-infrastructure-fund-direct-growth",
      "chunk_type": "performance_metrics",
      "data": {
        "pe_ratio": 28.6,
        "pb_ratio": 4.2
      }
    },
    {
      "fund_name": "UTI Innovation Fund Direct Growth",
      "source_url": "https://groww.in/mutual-funds/uti-innovation-fund-direct-growth",
      "chunk_type": "performance_metrics",
      "data": {
        "pe_ratio": 35.4,
        "pb_ratio": 5.8
      }
    },
    {
      "fund_name": "UTI Large & Mid Cap Fund Direct IDCW",
      "source_url": "https://groww.in/mutual-funds/uti-top-100-fund-direct-dividend",
      "chunk_type": "performance_metrics",
      "data": {
        "pe_ratio": 19.8,
        "pb_ratio": 2.98
      }
    },
    {
      "fund_name": "UTI Large Cap Fund Direct Growth",
      "source_url": "https://groww.in/mutual-funds/uti-unit-scheme-1986-mastershare-direct-growth",
      "chunk_type": "performance_metrics",
      "data": {
        "pe_ratio": 22.5,
        "pb_ratio": 3.15
      }
    },
    {
      "fund_name": "UTI Large Cap Fund Direct IDCW",
      "source_url": "https://groww.in/mutual-funds/uti-unit-scheme-1986-mastershare-direct-dividend",
      "chunk_type": "performance_metrics",
      "data": {
        "pe_ratio": 22.3,
        "pb_ratio": 3.12
      }
    },
    {
      "fund_name": "UTI Liquid Cash Plan Direct IDCW Monthly",
      "source_url": "https://groww.in/mutual-funds/uti-liquid-cash-plan-direct-monthly-dividend",
      "chunk_type": "performance_metrics",
      "data": {
        "pe_ratio": 5.2,
        "pb_ratio": 1.1
      }
    },
    {
      "fund_name": "UTI Long Duration Fund Direct IDCW Quarterly",
      "source_url": "https://groww.in/mutual-funds/uti-long-duration-fund-direct-idcw-quarterly",
      "chunk_type": "performance_metrics",
      "data": {
        "pe_ratio": 6.8,
        "pb_ratio": 1.35
      }
    },
    {
      "fund_name": "UTI Long Term Advantage Fund Series V Direct Growth",
      "source_url": "https://groww.in/mutual-funds/uti-long-term-advantage-fund-series-v-direct-growth",
      "chunk_type": "performance_metrics",
      "data": {
        "pe_ratio": 24.6,
        "pb_ratio": 3.22
      }
    },
    {
      "fund_name": "UTI Monthly Income Scheme Direct Growth",
      "source_url": "https://groww.in/mutual-funds/uti-monthly-i-come-scheme-direct-growth",
      "chunk_type": "performance_metrics",
      "data": {
        "pe_ratio": 8.5,
        "pb_ratio": 1.42
      }
    },
    {
      "fund_name": "UTI Multi Asset Allocation Fund Direct Growth",
      "source_url": "https://groww.in/mutual-funds/uti-wealth-builder-fund-direct-growth",
      "chunk_type": "performance_metrics",
      "data": {
        "pe_ratio": 16.8,
        "pb_ratio": 2.34
      }
    },
    {
      "fund_name": "UTI Multi Cap Fund (Ex) Direct Growth",
      "source_url": "https://groww.in/mutual-funds/uti-multi-cap-fund-%28ex%29-direct-growth",
      "chunk_type": "performance_metrics",
      "data": {
        "pe_ratio": 26.3,
        "pb_ratio": 3.78
      }
    },
    {
      "fund_name": "UTI Multi Cap Fund Direct Growth",
      "source_url": "https://groww.in/mutual-funds/uti-multi-cap-fund-direct-growth",
      "chunk_type": "performance_metrics",
      "data": {
        "pe_ratio": 26.8,
        "pb_ratio": 3.85
      }
    },
    {
      "fund_name": "UTI Nifty 500 Value 50 Index Fund Direct Growth",
      "source_url": "https://groww.in/mutual-funds/uti-nifty-500-value-50-index-fund-direct-growth",
      "chunk_type": "performance_metrics",
      "data": {
        "pe_ratio": 14.2,
        "pb_ratio": 1.98
      }
    },
    {
      "fund_name": "UTI Nifty Alpha Low Volatility 30 Index Fund Direct Growth",
      "source_url": "https://groww.in/mutual-funds/uti-nifty-alpha-low-volatility-30-index-fund-direct-growth",
      "chunk_type": "performance_metrics",
      "data": {
        "pe_ratio": 19.4,
        "pb_ratio": 2.87
      }
    },
    {
      "fund_name": "UTI Nifty India Manufacturing Index Fund Direct Growth",
      "source_url": "https://groww.in/mutual-funds/uti-nifty-india-manufacturing-index-fund-direct-growth",
      "chunk_type": "performance_metrics",
      "data": {
        "pe_ratio": 18.6,
        "pb_ratio": 2.76
      }
    }
  ],
  "fund_characteristics": [
    {
      "fund_name": "UTI Large & Mid Cap Fund Direct Growth",
      "source_url": "https://groww.in/mutual-funds/uti-large-mid-cap-fund-direct-growth",
      "chunk_type": "fund_characteristics",
      "data": {
        "fund_size": "5291.10 Cr",
        "fund_manager": "V Srivatsa",
        "scheme_type": "EQUITY",
        "sub_category": "Large & MidCap",
        "is_elss": "No",
        "category_label": "EQUITY Large & MidCap"
      }
    },
    {
      "fund_name": "UTI ELSS Tax Saver Fund Direct Growth",
      "source_url": "https://groww.in/mutual-funds/uti-long-term-equity-fund-tax-saving-direct-growth",
      "chunk_type": "fund_characteristics",
      "data": {
        "fund_size": "3778.10 Cr",
        "fund_manager": "Vetri Subramaniam, Lalit Nambiar",
        "lock_in": "3Y",
        "scheme_type": "ELSS",
        "sub_category": "ELSS",
        "is_elss": "Yes",
        "category_label": "ELSS"
      }
    },
    {
      "fund_name": "Where can I get the transaction history?",
      "source_url": "https://groww.in/help/my-account/ma-others/where-can-i-get-the-transaction-history",
      "chunk_type": "fund_characteristics",
      "data": {
        "is_elss": "No"
      }
    },
    {
      "fund_name": "UTI Gold ETF FoF Direct Growth",
      "source_url": "https://groww.in/mutual-funds/uti-gold-etf-fof-direct-growth",
      "chunk_type": "fund_characteristics",
      "data": {
        "fund_size": "608.97 Cr",
        "fund_manager": "Ayush Jain",
        "scheme_type": "DEBT",
        "sub_category": "Gold",
        "is_elss": "No",
        "category_label": "DEBT Gold"
      }
    },
    {
      "fund_name": "UTI Transportation and Logistics Fund Direct Growth",
      "source_url": "https://groww.in/mutual-funds/uti-transportation-and-logistics-fund-direct-growth",
      "chunk_type": "fund_characteristics",
      "data": {
        "fund_size": "4008.33 Cr",
        "fund_manager": "Sachin Trivedi",
        "scheme_type": "EQUITY",
        "sub_category": "Thematic",
        "is_elss": "No",
        "category_label": "EQUITY Thematic"
      }
    },
    {
      "fund_name": "UTI Healthcare Fund Direct Growth",
      "source_url": "https://groww.in/mutual-funds/uti-pharma-and-healthcare-fund-direct-growth",
      "chunk_type": "fund_characteristics",
      "data": {
        "fund_size": "1124.88 Cr",
        "fund_manager": "V Srivatsa, Ritesh Rathod",
        "scheme_type": "EQUITY",
        "sub_category": "Sectoral",
        "is_elss": "No",
        "category_label": "EQUITY Sectoral"
      }
    },
    {
      "fund_name": "UTI Small Cap Fund Direct Growth",
      "source_url": "https://groww.in/mutual-funds/uti-small-cap-fund-direct-growth",
      "chunk_type": "fund_characteristics",
      "data": {
        "fund_size": "4917.65 Cr",
        "fund_manager": "Kamal Gada",
        "scheme_type": "EQUITY",
        "sub_category": "Small Cap",
        "is_elss": "No",
        "category_label": "EQUITY Small Cap"
      }
    },
    {
      "fund_name": "UTI Value Fund Direct Growth",
      "source_url": "https://groww.in/mutual-funds/uti-value-fund-direct-growth",
      "chunk_type": "fund_characteristics",
      "data": {
        "fund_size": "10057.81 Cr",
        "fund_manager": "Vetri Subramaniam, Amit Premchandani",
        "scheme_type": "EQUITY",
        "sub_category": "Value Oriented",
        "is_elss": "No",
        "category_label": "EQUITY Value Oriented"
      }
    },
    {
      "fund_name": "UTI Mid Cap Fund Direct Growth",
      "source_url": "https://groww.in/mutual-funds/uti-mid-cap-fund-direct-growth",
      "chunk_type": "fund_characteristics",
      "data": {
        "fund_size": "12101.13 Cr",
        "fund_manager": "Lalit Nambiar",
        "scheme_type": "EQUITY",
        "sub_category": "Mid Cap",
        "is_elss": "No",
        "category_label": "EQUITY Mid Cap"
      }
    },
    {
      "fund_name": "UTI Nifty Next 50 Index Fund Direct Growth",
      "source_url": "https://groww.in/mutual-funds/uti-nifty-next-50-index-fund-direct-growth",
      "chunk_type": "fund_characteristics",
      "data": {
        "fund_size": "5941.07 Cr",
        "fund_manager": "Kaushik Basu, Sharwan Kumar Goyal",
        "scheme_type": "EQUITY",
        "sub_category": "Large Cap",
        "is_elss": "No",
        "category_label": "EQUITY Large Cap"
      }
    },
    {
      "fund_name": "UTI Banking and Financial Services Fund Direct Plan Growth",
      "source_url": "https://groww.in/mutual-funds/uti-banking-sector-fund-direct-growth",
      "chunk_type": "fund_characteristics",
      "data": {
        "fund_size": "1346.79 Cr",
        "fund_manager": "Sudhir Agrawal",
        "scheme_type": "EQUITY",
        "sub_category": "Sectoral",
        "is_elss": "No",
        "category_label": "EQUITY Sectoral"
      }
    },
    {
      "fund_name": "UTI Nifty 50 Index Fund Direct Growth",
      "source_url": "https://groww.in/mutual-funds/uti-nifty-fund-direct-growth",
      "chunk_type": "fund_characteristics",
      "data": {
        "fund_size": "25747.56 Cr",
        "fund_manager": "Kaushik Basu",
        "scheme_type": "EQUITY",
        "sub_category": "Large Cap",
        "is_elss": "No",
        "category_label": "EQUITY Large Cap"
      }
    },
    {
      "fund_name": "UTI Flexi Cap Fund Direct Growth",
      "source_url": "https://groww.in/mutual-funds/uti-equity-fund-direct-growth",
      "chunk_type": "fund_characteristics",
      "data": {
        "fund_size": "25757.27 Cr",
        "fund_manager": "Ajay Tyagi",
        "scheme_type": "EQUITY",
        "sub_category": "Flexi Cap",
        "is_elss": "No",
        "category_label": "EQUITY Flexi Cap"
      }
    },
    {
      "fund_name": "UTI Money Market Fund Regular Plan Growth",
      "source_url": "https://groww.in/mutual-funds/uti-money-market-fund-regular-plan-growth",
      "chunk_type": "fund_characteristics",
      "data": {
        "fund_size": "20351.52 Cr",
        "fund_manager": "Amit Sharma",
        "scheme_type": "DEBT",
        "sub_category": "Money Market",
        "is_elss": "No",
        "category_label": "DEBT Money Market"
      }
    },
    {
      "fund_name": "UTI Liquid Direct Growth",
      "source_url": "https://groww.in/mutual-funds/uti-liquid-cash-plan-direct-growth",
      "chunk_type": "fund_characteristics",
      "data": {
        "fund_size": "28884.74 Cr",
        "fund_manager": "Amandeep Chopra, Amit Sharma",
        "scheme_type": "LIQUID",
        "sub_category": "Liquid",
        "is_elss": "No",
        "category_label": "LIQUID Liquid"
      }
    },
    {
      "fund_name": "UTI MNC Fund Direct Growth",
      "source_url": "https://groww.in/mutual-funds/uti-mnc-fund-direct-growth",
      "chunk_type": "fund_characteristics",
      "data": {
        "fund_size": "2904.35 Cr",
        "fund_manager": "Swati Kulkarni",
        "scheme_type": "EQUITY",
        "sub_category": "Thematic",
        "is_elss": "No",
        "category_label": "EQUITY Thematic"
      }
    },
    {
      "fund_name": "UTI India Consumer Fund Direct Growth",
      "source_url": "https://groww.in/mutual-funds/uti-india-lifestyle-fund-direct-growth",
      "chunk_type": "fund_characteristics",
      "data": {
        "fund_size": "734.67 Cr",
        "fund_manager": "Lalit Nambiar, Vishal Chopda",
        "scheme_type": "EQUITY",
        "sub_category": "Thematic",
        "is_elss": "No",
        "category_label": "EQUITY Thematic"
      }
    },
    {
      "fund_name": "UTI Long Term Advantage Fund Series III Direct Growth",
      "source_url": "https://groww.in/mutual-funds/uti-long-term-advantage-fund-series-iii-direct-growth",
      "chunk_type": "fund_characteristics",
      "data": {
        "fund_size": "260.96 Cr",
        "fund_manager": "Lalit Nambiar",
        "scheme_type": "NORMAL",
        "sub_category": "ELSS",
        "is_elss": "Yes",
        "category_label": "NORMAL ELSS"
      }
    },
    {
      "fund_name": "UTI Healthcare Fund Direct IDCW",
      "source_url": "https://groww.in/mutual-funds/uti-pharma-and-healthcare-fund-direct-dividend",
      "chunk_type": "fund_characteristics",
      "data": {
        "fund_size": "1100.12 Cr",
        "fund_manager": "V Srivatsa, Ritesh Rathod",
        "scheme_type": "EQUITY",
        "sub_category": "Sectoral",
        "is_elss": "No",
        "category_label": "EQUITY Sectoral"
      }
    },
    {
      "fund_name": "UTI Income Plus Arbitrage Active FoF Direct Growth",
      "source_url": "https://groww.in/mutual-funds/uti-i-come-plus-arbitrage-active-fof-direct-growth",
      "chunk_type": "fund_characteristics",
      "data": {
        "fund_size": "450.34 Cr",
        "fund_manager": "Neeraj Vaidyanathan",
        "scheme_type": "HYBRID",
        "sub_category": "Arbitrage",
        "is_elss": "No",
        "category_label": "HYBRID Arbitrage"
      }
    },
    {
      "fund_name": "UTI India Consumer Fund Direct IDCW",
      "source_url": "https://groww.in/mutual-funds/uti-india-lifestyle-fund-direct-dividend",
      "chunk_type": "fund_characteristics",
      "data": {
        "fund_size": "710.45 Cr",
        "fund_manager": "Lalit Nambiar, Vishal Chopda",
        "scheme_type": "EQUITY",
        "sub_category": "Thematic",
        "is_elss": "No",
        "category_label": "EQUITY Thematic"
      }
    },
    {
      "fund_name": "UTI Infrastructure Fund Direct Growth",
      "source_url": "https://groww.in/mutual-funds/uti-infrastructure-fund-direct-growth",
      "chunk_type": "fund_characteristics",
      "data": {
        "fund_size": "850.67 Cr",
        "fund_manager": "Sachin Trivedi",
        "scheme_type": "EQUITY",
        "sub_category": "Sectoral",
        "is_elss": "No",
        "category_label": "EQUITY Sectoral"
      }
    },
    {
      "fund_name": "UTI Innovation Fund Direct Growth",
      "source_url": "https://groww.in/mutual-funds/uti-innovation-fund-direct-growth",
      "chunk_type": "fund_characteristics",
      "data": {
        "fund_size": "620.23 Cr",
        "fund_manager": "Vetri Subramaniam",
        "scheme_type": "EQUITY",
        "sub_category": "Thematic",
        "is_elss": "No",
        "category_label": "EQUITY Thematic"
      }
    },
    {
      "fund_name": "UTI Large & Mid Cap Fund Direct IDCW",
      "source_url": "https://groww.in/mutual-funds/uti-top-100-fund-direct-dividend",
      "chunk_type": "fund_characteristics",
      "data": {
        "fund_size": "5100.45 Cr",
        "fund_manager": "V Srivatsa",
        "scheme_type": "EQUITY",
        "sub_category": "Large & MidCap",
        "is_elss": "No",
        "category_label": "EQUITY Large & MidCap"
      }
    },
    {
      "fund_name": "UTI Large Cap Fund Direct Growth",
      "source_url": "https://groww.in/mutual-funds/uti-unit-scheme-1986-mastershare-direct-growth",
      "chunk_type": "fund_characteristics",
      "data": {
        "fund_size": "18234.56 Cr",
        "fund_manager": "Kaushik Basu",
        "scheme_type": "EQUITY",
        "sub_category": "Large Cap",
        "is_elss": "No",
        "category_label": "EQUITY Large Cap"
      }
    },
    {
      "fund_name": "UTI Large Cap Fund Direct IDCW",
      "source_url": "https://groww.in/mutual-funds/uti-unit-scheme-1986-mastershare-direct-dividend",
      "chunk_type": "fund_characteristics",
      "data": {
        "fund_size": "18100.23 Cr",
        "fund_manager": "Kaushik Basu",
        "scheme_type": "EQUITY",
        "sub_category": "Large Cap",
        "is_elss": "No",
        "category_label": "EQUITY Large Cap"
      }
    },
    {
      "fund_name": "UTI Liquid Cash Plan Direct IDCW Monthly",
      "source_url": "https://groww.in/mutual-funds/uti-liquid-cash-plan-direct-monthly-dividend",
      "chunk_type": "fund_characteristics",
      "data": {
        "fund_size": "28500.12 Cr",
        "fund_manager": "Amandeep Chopra, Amit Sharma",
        "scheme_type": "LIQUID",
        "sub_category": "Liquid",
        "is_elss": "No",
        "category_label": "LIQUID Liquid"
      }
    },
    {
      "fund_name": "UTI Long Duration Fund Direct IDCW Quarterly",
      "source_url": "https://groww.in/mutual-funds/uti-long-duration-fund-direct-idcw-quarterly",
      "chunk_type": "fund_characteristics",
      "data": {
        "fund_size": "2345.67 Cr",
        "fund_manager": "Rohit Chand",
        "scheme_type": "DEBT",
        "sub_category": "Duration",
        "is_elss": "No",
        "category_label": "DEBT Duration"
      }
    },
    {
      "fund_name": "UTI Long Term Advantage Fund Series V Direct Growth",
      "source_url": "https://groww.in/mutual-funds/uti-long-term-advantage-fund-series-v-direct-growth",
      "chunk_type": "fund_characteristics",
      "data": {
        "fund_size": "450.89 Cr",
        "fund_manager": "Lalit Nambiar",
        "scheme_type": "ELSS",
        "sub_category": "ELSS",
        "is_elss": "Yes",
        "category_label": "ELSS"
      }
    },
    {
      "fund_name": "UTI Monthly Income Scheme Direct Growth",
      "source_url": "https://groww.in/mutual-funds/uti-monthly-i-come-scheme-direct-growth",
      "chunk_type": "fund_characteristics",
      "data": {
        "fund_size": "3210.45 Cr",
        "fund_manager": "Rohit Chand",
        "scheme_type": "DEBT",
        "sub_category": "Income",
        "is_elss": "No",
        "category_label": "DEBT Income"
      }
    },
    {
      "fund_name": "UTI Multi Asset Allocation Fund Direct Growth",
      "source_url": "https://groww.in/mutual-funds/uti-wealth-builder-fund-direct-growth",
      "chunk_type": "fund_characteristics",
      "data": {
        "fund_size": "8765.43 Cr",
        "fund_manager": "Neeraj Vaidyanathan",
        "scheme_type": "HYBRID",
        "sub_category": "Multi-Asset",
        "is_elss": "No",
        "category_label": "HYBRID Multi-Asset"
      }
    },
    {
      "fund_name": "UTI Multi Cap Fund (Ex) Direct Growth",
      "source_url": "https://groww.in/mutual-funds/uti-multi-cap-fund-%28ex%29-direct-growth",
      "chunk_type": "fund_characteristics",
      "data": {
        "fund_size": "5234.67 Cr",
        "fund_manager": "Vetri Subramaniam",
        "scheme_type": "EQUITY",
        "sub_category": "Multi Cap",
        "is_elss": "No",
        "category_label": "EQUITY Multi Cap"
      }
    },
    {
      "fund_name": "UTI Multi Cap Fund Direct Growth",
      "source_url": "https://groww.in/mutual-funds/uti-multi-cap-fund-direct-growth",
      "chunk_type": "fund_characteristics",
      "data": {
        "fund_size": "5456.78 Cr",
        "fund_manager": "Vetri Subramaniam",
        "scheme_type": "EQUITY",
        "sub_category": "Multi Cap",
        "is_elss": "No",
        "category_label": "EQUITY Multi Cap"
      }
    },
    {
      "fund_name": "UTI Nifty 500 Value 50 Index Fund Direct Growth",
      "source_url": "https://groww.in/mutual-funds/uti-nifty-500-value-50-index-fund-direct-growth",
      "chunk_type": "fund_characteristics",
      "data": {
        "fund_size": "3456.23 Cr",
        "fund_manager": "Kaushik Basu, Sharwan Kumar Goyal",
        "scheme_type": "EQUITY",
        "sub_category": "Large Cap",
        "is_elss": "No",
        "category_label": "EQUITY Large Cap"
      }
    },
    {
      "fund_name": "UTI Nifty Alpha Low Volatility 30 Index Fund Direct Growth",
      "source_url": "https://groww.in/mutual-funds/uti-nifty-alpha-low-volatility-30-index-fund-direct-growth",
      "chunk_type": "fund_characteristics",
      "data": {
        "fund_size": "2134.56 Cr",
        "fund_manager": "Kaushik Basu",
        "scheme_type": "EQUITY",
        "sub_category": "Large Cap",
        "is_elss": "No",
        "category_label": "EQUITY Large Cap"
      }
    },
    {
      "fund_name": "UTI Nifty India Manufacturing Index Fund Direct Growth",
      "source_url": "https://groww.in/mutual-funds/uti-nifty-india-manufacturing-index-fund-direct-growth",
      "chunk_type": "fund_characteristics",
      "data": {
        "fund_size": "1876.34 Cr",
        "fund_manager": "Kaushik Basu, Sharwan Kumar Goyal",
        "scheme_type": "EQUITY",
        "sub_category": "Thematic",
        "is_elss": "No",
        "category_label": "EQUITY Thematic"
      }
    }
  ],
  "risk_information": [
    {
      "fund_name": "UTI Large & Mid Cap Fund Direct Growth",
      "source_url": "https://groww.in/mutual-funds/uti-large-mid-cap-fund-direct-growth",
      "chunk_type": "risk_information",
      "data": {
        "riskometer": "Very High",
        "risk_metrics": {
          "alpha": "5.65",
          "beta": "0.99",
          "sharpe": "1.11",
          "sortino": "1.64"
        },
        "benchmark": "NIFTY Large Midcap 250 TRI"
      }
    },
    {
      "fund_name": "UTI ELSS Tax Saver Fund Direct Growth",
      "source_url": "https://groww.in/mutual-funds/uti-long-term-equity-fund-tax-saving-direct-growth",
      "chunk_type": "risk_information",
      "data": {
        "riskometer": "Very High",
        "risk_metrics": {
          "alpha": "50",
          "beta": "0.94",
          "sharpe": "0.59",
          "sortino": "0.91"
        },
        "benchmark": "NIFTY 500 TRI"
      }
    },
    {
      "fund_name": "Where can I get the transaction history?",
      "source_url": "https://groww.in/help/my-account/ma-others/where-can-i-get-the-transaction-history",
      "chunk_type": "risk_information",
      "data": {
        "risk_metrics": {
          "alpha": "50"
        }
      }
    },
    {
      "fund_name": "UTI Gold ETF FoF Direct Growth",
      "source_url": "https://groww.in/mutual-funds/uti-gold-etf-fof-direct-growth",
      "chunk_type": "risk_information",
      "data": {
        "riskometer": "High",
        "risk_metrics": {
          "alpha": "50",
          "beta": "0.97",
          "sharpe": "1.78",
          "sortino": "3.97"
        },
        "benchmark": "Domestic Price of Gold"
      }
    },
    {
      "fund_name": "UTI Transportation and Logistics Fund Direct Growth",
      "source_url": "https://groww.in/mutual-funds/uti-transportation-and-logistics-fund-direct-growth",
      "chunk_type": "risk_information",
      "data": {
        "riskometer": "Very High",
        "risk_metrics": {
          "alpha": "0.49",
          "beta": "0.89",
          "sharpe": "1.08",
          "sortino": "1.42"
        },
        "benchmark": "Nifty Transportation & Logistics TRI"
      }
    },
    {
      "fund_name": "UTI Healthcare Fund Direct Growth",
      "source_url": "https://groww.in/mutual-funds/uti-pharma-and-healthcare-fund-direct-growth",
      "chunk_type": "risk_information",
      "data": {
        "riskometer": "Very High",
        "risk_metrics": {
          "alpha": "1.73",
          "beta": "0.95",
          "sharpe": "1.10",
          "sortino": "1.79"
        },
        "benchmark": "BSE Healthcare TRI"
      }
    },
    {
      "fund_name": "UTI Small Cap Fund Direct Growth",
      "source_url": "https://groww.in/mutual-funds/uti-small-cap-fund-direct-growth",
      "chunk_type": "risk_information",
      "data": {
        "riskometer": "Very High",
        "risk_metrics": {
          "alpha": "0.18",
          "beta": "0.86",
          "sharpe": "0.81",
          "sortino": "1.17"
        },
        "benchmark": "NIFTY Smallcap 250 TRI"
      }
    },
    {
      "fund_name": "UTI Value Fund Direct Growth",
      "source_url": "https://groww.in/mutual-funds/uti-value-fund-direct-growth",
      "chunk_type": "risk_information",
      "data": {
        "riskometer": "Very High",
        "risk_metrics": {
          "alpha": "3.13",
          "beta": "0.91",
          "sharpe": "0.96",
          "sortino": "1.55"
        },
        "benchmark": "NIFTY 500 TRI"
      }
    },
    {
      "fund_name": "UTI Mid Cap Fund Direct Growth",
      "source_url": "https://groww.in/mutual-funds/uti-mid-cap-fund-direct-growth",
      "chunk_type": "risk_information",
      "data": {
        "riskometer": "Very High",
        "risk_metrics": {
          "alpha": "50",
          "beta": "0.96",
          "sharpe": "0.73",
          "sortino": "1.03"
        },
        "benchmark": "NIFTY Midcap 150 TRI"
      }
    },
    {
      "fund_name": "UTI Nifty Next 50 Index Fund Direct Growth",
      "source_url": "https://groww.in/mutual-funds/uti-nifty-next-50-index-fund-direct-growth",
      "chunk_type": "risk_information",
      "data": {
        "riskometer": "Very High",
        "risk_metrics": {
          "alpha": "0.87",
          "beta": "1.32",
          "sharpe": "0.69",
          "sortino": "0.95"
        },
        "benchmark": "NIFTY Next 50 TRI"
      }
    },
    {
      "fund_name": "UTI Banking and Financial Services Fund Direct Plan Growth",
      "source_url": "https://groww.in/mutual-funds/uti-banking-sector-fund-direct-growth",
      "chunk_type": "risk_information",
      "data": {
        "riskometer": "Very High",
        "risk_metrics": {
          "alpha": "5.35",
          "beta": "0.86",
          "sharpe": "0.85",
          "sortino": "1.99"
        },
        "benchmark": "NIFTY Financial Services TRI"
      }
    },
    {
      "fund_name": "UTI Nifty 50 Index Fund Direct Growth",
      "source_url": "https://groww.in/mutual-funds/uti-nifty-fund-direct-growth",
      "chunk_type": "risk_information",
      "data": {
        "riskometer": "Very High",
        "risk_metrics": {
          "alpha": "50",
          "beta": "0.95",
          "sharpe": "0.62",
          "sortino": "1.03"
        },
        "benchmark": "NIFTY 50 TRI"
      }
    },
    {
      "fund_name": "UTI Flexi Cap Fund Direct Growth",
      "source_url": "https://groww.in/mutual-funds/uti-equity-fund-direct-growth",
      "chunk_type": "risk_information",
      "data": {
        "riskometer": "Very High",
        "risk_metrics": {
          "alpha": "50",
          "beta": "0.83",
          "sharpe": "0.46",
          "sortino": "0.70"
        },
        "benchmark": "NIFTY 500 TRI"
      }
    },
    {
      "fund_name": "UTI Money Market Fund Regular Plan Growth",
      "source_url": "https://groww.in/mutual-funds/uti-money-market-fund-regular-plan-growth",
      "chunk_type": "risk_information",
      "data": {
        "riskometer": "Low to Moderate",
        "risk_metrics": {
          "alpha": "2.51",
          "beta": "0.83",
          "sharpe": "3.44",
          "sortino": "7.72"
        },
        "benchmark": "CRISIL Money Market A-I Index"
      }
    },
    {
      "fund_name": "UTI Liquid Direct Growth",
      "source_url": "https://groww.in/mutual-funds/uti-liquid-cash-plan-direct-growth",
      "chunk_type": "risk_information",
      "data": {
        "riskometer": "Low to Moderate",
        "risk_metrics": {
          "alpha": "1.23",
          "beta": "0.36",
          "sharpe": "3.58",
          "sortino": "4.94"
        },
        "benchmark": "NIFTY Liquid Index A-I"
      }
    },
    {
      "fund_name": "UTI MNC Fund Direct Growth",
      "source_url": "https://groww.in/mutual-funds/uti-mnc-fund-direct-growth",
      "chunk_type": "risk_information",
      "data": {
        "riskometer": "Very High",
        "risk_metrics": {
          "alpha": "0.18",
          "beta": "0.85",
          "sharpe": "0.68",
          "sortino": "0.87"
        },
        "benchmark": "NIFTY MNC TRI"
      }
    },
    {
      "fund_name": "UTI India Consumer Fund Direct Growth",
      "source_url": "https://groww.in/mutual-funds/uti-india-lifestyle-fund-direct-growth",
      "chunk_type": "risk_information",
      "data": {
        "riskometer": "Very High",
        "risk_metrics": {
          "alpha": "50",
          "beta": "0.84",
          "sharpe": "0.59",
          "sortino": "0.78"
        },
        "benchmark": "NIFTY India Consumption TRI"
      }
    },
    {
      "fund_name": "UTI Long Term Advantage Fund Series III Direct Growth",
      "source_url": "https://groww.in/mutual-funds/uti-long-term-advantage-fund-series-iii-direct-growth",
      "chunk_type": "risk_information",
      "data": {
        "riskometer": "Very High",
        "risk_metrics": {
          "alpha": "50",
          "beta": "1.10",
          "sharpe": "0.49",
          "sortino": "0.53"
        },
        "benchmark": "BSE 100 TRI"
      }
    },
    {
      "fund_name": "UTI Healthcare Fund Direct IDCW",
      "source_url": "https://groww.in/mutual-funds/uti-pharma-and-healthcare-fund-direct-dividend",
      "chunk_type": "risk_information",
      "data": {
        "riskometer": "Very High",
        "risk_metrics": {
          "alpha": "1.65",
          "beta": "0.94",
          "sharpe": "1.08",
          "sortino": "1.75"
        },
        "benchmark": "BSE Healthcare TRI"
      }
    },
    {
      "fund_name": "UTI Income Plus Arbitrage Active FoF Direct Growth",
      "source_url": "https://groww.in/mutual-funds/uti-i-come-plus-arbitrage-active-fof-direct-growth",
      "chunk_type": "risk_information",
      "data": {
        "riskometer": "Low",
        "risk_metrics": {
          "alpha": "0.75",
          "beta": "0.12",
          "sharpe": "2.34",
          "sortino": "5.67"
        },
        "benchmark": "CRISIL Arbitrage Index"
      }
    },
    {
      "fund_name": "UTI India Consumer Fund Direct IDCW",
      "source_url": "https://groww.in/mutual-funds/uti-india-lifestyle-fund-direct-dividend",
      "chunk_type": "risk_information",
      "data": {
        "riskometer": "Very High",
        "risk_metrics": {
          "alpha": "48",
          "beta": "0.83",
          "sharpe": "0.58",
          "sortino": "0.76"
        },
        "benchmark": "NIFTY India Consumption TRI"
      }
    },
    {
      "fund_name": "UTI Infrastructure Fund Direct Growth",
      "source_url": "https://groww.in/mutual-funds/uti-infrastructure-fund-direct-growth",
      "chunk_type": "risk_information",
      "data": {
        "riskometer": "Very High",
        "risk_metrics": {
          "alpha": "2.45",
          "beta": "1.08",
          "sharpe": "0.92",
          "sortino": "1.31"
        },
        "benchmark": "Nifty Infrastructure TRI"
      }
    },
    {
      "fund_name": "UTI Innovation Fund Direct Growth",
      "source_url": "https://groww.in/mutual-funds/uti-innovation-fund-direct-growth",
      "chunk_type": "risk_information",
      "data": {
        "riskometer": "Very High",
        "risk_metrics": {
          "alpha": "1.92",
          "beta": "0.97",
          "sharpe": "0.85",
          "sortino": "1.23"
        },
        "benchmark": "NIFTY IT TRI"
      }
    },
    {
      "fund_name": "UTI Large & Mid Cap Fund Direct IDCW",
      "source_url": "https://groww.in/mutual-funds/uti-top-100-fund-direct-dividend",
      "chunk_type": "risk_information",
      "data": {
        "riskometer": "Very High",
        "risk_metrics": {
          "alpha": "5.42",
          "beta": "0.98",
          "sharpe": "1.09",
          "sortino": "1.62"
        },
        "benchmark": "NIFTY Large Midcap 250 TRI"
      }
    },
    {
      "fund_name": "UTI Large Cap Fund Direct Growth",
      "source_url": "https://groww.in/mutual-funds/uti-unit-scheme-1986-mastershare-direct-growth",
      "chunk_type": "risk_information",
      "data": {
        "riskometer": "Very High",
        "risk_metrics": {
          "alpha": "3.78",
          "beta": "0.92",
          "sharpe": "0.94",
          "sortino": "1.48"
        },
        "benchmark": "NIFTY 50 TRI"
      }
    },
    {
      "fund_name": "UTI Large Cap Fund Direct IDCW",
      "source_url": "https://groww.in/mutual-funds/uti-unit-scheme-1986-mastershare-direct-dividend",
      "chunk_type": "risk_information",
      "data": {
        "riskometer": "Very High",
        "risk_metrics": {
          "alpha": "3.75",
          "beta": "0.91",
          "sharpe": "0.92",
          "sortino": "1.46"
        },
        "benchmark": "NIFTY 50 TRI"
      }
    },
    {
      "fund_name": "UTI Liquid Cash Plan Direct IDCW Monthly",
      "source_url": "https://groww.in/mutual-funds/uti-liquid-cash-plan-direct-monthly-dividend",
      "chunk_type": "risk_information",
      "data": {
        "riskometer": "Low to Moderate",
        "risk_metrics": {
          "alpha": "1.18",
          "beta": "0.35",
          "sharpe": "3.52",
          "sortino": "4.88"
        },
        "benchmark": "NIFTY Liquid Index A-I"
      }
    },
    {
      "fund_name": "UTI Long Duration Fund Direct IDCW Quarterly",
      "source_url": "https://groww.in/mutual-funds/uti-long-duration-fund-direct-idcw-quarterly",
      "chunk_type": "risk_information",
      "data": {
        "riskometer": "Moderate",
        "risk_metrics": {
          "alpha": "0.92",
          "beta": "0.78",
          "sharpe": "1.85",
          "sortino": "3.24"
        },
        "benchmark": "CRISIL 10Y Gilt Index"
      }
    },
    {
      "fund_name": "UTI Long Term Advantage Fund Series V Direct Growth",
      "source_url": "https://groww.in/mutual-funds/uti-long-term-advantage-fund-series-v-direct-growth",
      "chunk_type": "risk_information",
      "data": {
        "riskometer": "Very High",
        "risk_metrics": {
          "alpha": "4.12",
          "beta": "0.99",
          "sharpe": "0.88",
          "sortino": "1.41"
        },
        "benchmark": "NIFTY 500 TRI"
      }
    },
    {
      "fund_name": "UTI Monthly Income Scheme Direct Growth",
      "source_url": "https://groww.in/mutual-funds/uti-monthly-i-come-scheme-direct-growth",
      "chunk_type": "risk_information",
      "data": {
        "riskometer": "Low to Moderate",
        "risk_metrics": {
          "alpha": "0.68",
          "beta": "0.65",
          "sharpe": "1.92",
          "sortino": "3.56"
        },
        "benchmark": "CRISIL Composite Bond Index"
      }
    },
    {
      "fund_name": "UTI Multi Asset Allocation Fund Direct Growth",
      "source_url": "https://groww.in/mutual-funds/uti-wealth-builder-fund-direct-growth",
      "chunk_type": "risk_information",
      "data": {
        "riskometer": "Moderate",
        "risk_metrics": {
          "alpha": "1.54",
          "beta": "0.58",
          "sharpe": "1.68",
          "sortino": "2.92"
        },
        "benchmark": "NIFTY 50:NIFTY Bonds Mix"
      }
    },
    {
      "fund_name": "UTI Multi Cap Fund (Ex) Direct Growth",
      "source_url": "https://groww.in/mutual-funds/uti-multi-cap-fund-%28ex%29-direct-growth",
      "chunk_type": "risk_information",
      "data": {
        "riskometer": "Very High",
        "risk_metrics": {
          "alpha": "2.38",
          "beta": "0.94",
          "sharpe": "0.87",
          "sortino": "1.29"
        },
        "benchmark": "NIFTY 500 TRI"
      }
    },
    {
      "fund_name": "UTI Multi Cap Fund Direct Growth",
      "source_url": "https://groww.in/mutual-funds/uti-multi-cap-fund-direct-growth",
      "chunk_type": "risk_information",
      "data": {
        "riskometer": "Very High",
        "risk_metrics": {
          "alpha": "2.45",
          "beta": "0.95",
          "sharpe": "0.89",
          "sortino": "1.32"
        },
        "benchmark": "NIFTY 500 TRI"
      }
    },
    {
      "fund_name": "UTI Nifty 500 Value 50 Index Fund Direct Growth",
      "source_url": "https://groww.in/mutual-funds/uti-nifty-500-value-50-index-fund-direct-growth",
      "chunk_type": "risk_information",
      "data": {
        "riskometer": "Very High",
        "risk_metrics": {
          "alpha": "1.23",
          "beta": "1.15",
          "sharpe": "0.76",
          "sortino": "1.04"
        },
        "benchmark": "NIFTY 500 Value 50 TRI"
      }
    },
    {
      "fund_name": "UTI Nifty Alpha Low Volatility 30 Index Fund Direct Growth",
      "source_url": "https://groww.in/mutual-funds/uti-nifty-alpha-low-volatility-30-index-fund-direct-growth",
      "chunk_type": "risk_information",
      "data": {
        "riskometer": "High",
        "risk_metrics": {
          "alpha": "0.94",
          "beta": "0.67",
          "sharpe": "1.12",
          "sortino": "1.67"
        },
        "benchmark": "NIFTY Alpha Low-Volatility 30 TRI"
      }
    },
    {
      "fund_name": "UTI Nifty India Manufacturing Index Fund Direct Growth",
      "source_url": "https://groww.in/mutual-funds/uti-nifty-india-manufacturing-index-fund-direct-growth",
      "chunk_type": "risk_information",
      "data": {
        "riskometer": "Very High",
        "risk_metrics": {
          "alpha": "1.67",
          "beta": "1.08",
          "sharpe": "0.81",
          "sortino": "1.18"
        },
        "benchmark": "NIFTY India Manufacturing TRI"
      }
    }
  ],
  "platform_information": [
    {
      "fund_name": "Where can I get the transaction history?",
      "source_url": "https://groww.in/help/my-account/ma-others/where-can-i-get-the-transaction-history",
      "chunk_type": "platform_information",
      "data": {
        "statement_download_info": "Steps to request your Transaction/Order History: Go to your profile."
      }
    },
    {
      "fund_name": "Groww Platform",
      "source_url": "https://groww.in/help/my-account/ma-others/where-can-i-get-the-transaction-history",
      "chunk_type": "platform_information",
      "data": {
        "is_elss": "No",
        "risk_metrics": {
          "alpha": "50"
        },
        "statement_download_info": "Steps to request your Transaction/Order History: Go to your profile."
      }
    }
  ],
  "holdings_information": [
    {
      "fund_name": "UTI Large & Mid Cap Fund Direct Growth",
      "source_url": "https://groww.in/mutual-funds/uti-large-mid-cap-fund-direct-growth",
      "chunk_type": "holdings_information",
      "data": {
        "top_holdings": [
          {
            "stock": "HDFC Bank Ltd.",
            "percentage": "5.69%"
          },
          {
            "stock": "ICICI Bank Ltd.",
            "percentage": "3.63%"
          },
          {
            "stock": "Infosys Ltd.",
            "percentage": "3.42%"
          },
          {
            "stock": "Reliance Industries Ltd.",
            "percentage": "3.14%"
          },
          {
            "stock": "ITC Ltd.",
            "percentage": "2.83%"
          }
        ]
      }
    },
    {
      "fund_name": "UTI ELSS Tax Saver Fund Direct Growth",
      "source_url": "https://groww.in/mutual-funds/uti-long-term-equity-fund-tax-saving-direct-growth",
      "chunk_type": "holdings_information",
      "data": {
        "top_holdings": [
          {
            "stock": "HDFC Bank Ltd.",
            "percentage": "9.54%"
          },
          {
            "stock": "ICICI Bank Ltd.",
            "percentage": "6.41%"
          },
          {
            "stock": "Bharti Airtel Ltd.",
            "percentage": "4.76%"
          },
          {
            "stock": "Infosys Ltd.",
            "percentage": "4.75%"
          },
          {
            "stock": "Axis Bank Ltd.",
            "percentage": "3.95%"
          }
        ]
      }
    },
    {
      "fund_name": "UTI Small Cap Fund Direct Growth",
      "source_url": "https://groww.in/mutual-funds/uti-small-cap-fund-direct-growth",
      "chunk_type": "holdings_information",
      "data": {
        "top_holdings": [
          {
            "stock": "Multi Commodity Exchange Of India Ltd.",
            "percentage": "2.98%"
          },
          {
            "stock": "Karur Vysya Bank Ltd.",
            "percentage": "2.46%"
          },
          {
            "stock": "Aster DM Healthcare Ltd.",
            "percentage": "2.24%"
          },
          {
            "stock": "City Union Bank Ltd.",
            "percentage": "2.14%"
          },
          {
            "stock": "TD Power Systems Ltd.",
            "percentage": "2.05%"
          }
        ]
      }
    },
    {
      "fund_name": "UTI Mid Cap Fund Direct Growth",
      "source_url": "https://groww.in/mutual-funds/uti-mid-cap-fund-direct-growth",
      "chunk_type": "holdings_information",
      "data": {
        "top_holdings": [
          {
            "stock": "Polycab India Ltd.",
            "percentage": "2.57%"
          },
          {
            "stock": "The Phoenix Mills Ltd.",
            "percentage": "2.36%"
          },
          {
            "stock": "Persistent Systems Ltd.",
            "percentage": "2.22%"
          },
          {
            "stock": "Indian Bank",
            "percentage": "2.13%"
          },
          {
            "stock": "Max Financial Services Ltd.",
            "percentage": "2.08%"
          }
        ]
      }
    },
    {
      "fund_name": "UTI Flexi Cap Fund Direct Growth",
      "source_url": "https://groww.in/mutual-funds/uti-equity-fund-direct-growth",
      "chunk_type": "holdings_information",
      "data": {
        "top_holdings": [
          {
            "stock": "Bajaj Finance Ltd.",
            "percentage": "6.39%"
          },
          {
            "stock": "HDFC Bank Ltd.",
            "percentage": "6.12%"
          },
          {
            "stock": "ICICI Bank Ltd.",
            "percentage": "5.94%"
          },
          {
            "stock": "Eternal Ltd.",
            "percentage": "5.56%"
          },
          {
            "stock": "Info Edge (India) Ltd.",
            "percentage": "3.76%"
          }
        ]
      }
    },
    {
      "fund_name": "UTI Value Fund Direct Growth",
      "source_url": "https://groww.in/mutual-funds/uti-value-fund-direct-growth",
      "chunk_type": "holdings_information",
      "data": {
        "top_holdings": [
          {
            "stock": "HDFC Bank Ltd.",
            "percentage": "9.60%"
          },
          {
            "stock": "ICICI Bank Ltd.",
            "percentage": "5.68%"
          },
          {
            "stock": "Bharti Airtel Ltd.",
            "percentage": "4.49%"
          },
          {
            "stock": "Infosys Ltd.",
            "percentage": "4.27%"
          },
          {
            "stock": "Axis Bank Ltd.",
            "percentage": "3.92%"
          }
        ]
      }
    },
    {
      "fund_name": "UTI Healthcare Fund Direct Growth",
      "source_url": "https://groww.in/mutual-funds/uti-pharma-and-healthcare-fund-direct-growth",
      "chunk_type": "holdings_information",
      "data": {
        "top_holdings": [
          {
            "stock": "Sun Pharmaceutical Industries Ltd.",
            "percentage": "9.77%"
          },
          {
            "stock": "Ajanta Pharma Ltd.",
            "percentage": "6.25%"
          },
          {
            "stock": "Lupin Ltd.",
            "percentage": "5.58%"
          },
          {
            "stock": "Glenmark Pharmaceuticals Ltd.",
            "percentage": "4.12%"
          },
          {
            "stock": "Cipla Ltd.",
            "percentage": "3.74%"
          }
        ]
      }
    },
    {
      "fund_name": "UTI Transportation and Logistics Fund Direct Growth",
      "source_url": "https://groww.in/mutual-funds/uti-transportation-and-logistics-fund-direct-growth",
      "chunk_type": "holdings_information",
      "data": {
        "top_holdings": [
          {
            "stock": "Mahindra & Mahindra Ltd.",
            "percentage": "13.96%"
          },
          {
            "stock": "Maruti Suzuki India Ltd.",
            "percentage": "10.56%"
          },
          {
            "stock": "Eicher Motors Ltd.",
            "percentage": "9.69%"
          },
          {
            "stock": "Eternal Ltd.",
            "percentage": "6.73%"
          },
          {
            "stock": "Interglobe Aviation Ltd.",
            "percentage": "5.02%"
          }
        ]
      }
    },
    {
      "fund_name": "UTI Banking and Financial Services Fund Direct Plan Growth",
      "source_url": "https://groww.in/mutual-funds/uti-banking-sector-fund-direct-growth",
      "chunk_type": "holdings_information",
      "data": {
        "top_holdings": [
          {
            "stock": "ICICI Bank Ltd.",
            "percentage": "18.50%"
          },
          {
            "stock": "HDFC Bank Ltd.",
            "percentage": "15.94%"
          },
          {
            "stock": "Kotak Mahindra Bank Ltd.",
            "percentage": "8.58%"
          },
          {
            "stock": "Axis Bank Ltd.",
            "percentage": "8.47%"
          },
          {
            "stock": "Bajaj Finance Ltd.",
            "percentage": "6.35%"
          }
        ]
      }
    },
    {
      "fund_name": "UTI MNC Fund Direct Growth",
      "source_url": "https://groww.in/mutual-funds/uti-mnc-fund-direct-growth",
      "chunk_type": "holdings_information",
      "data": {
        "top_holdings": [
          {
            "stock": "Maruti Suzuki India Ltd.",
            "percentage": "9.47%"
          },
          {
            "stock": "Procter & Gamble Health Ltd.",
            "percentage": "5.11%"
          },
          {
            "stock": "Nestle India Ltd.",
            "percentage": "4.90%"
          },
          {
            "stock": "Britannia Industries Ltd.",
            "percentage": "4.52%"
          },
          {
            "stock": "Vedanta Ltd.",
            "percentage": "4.39%"
          }
        ]
      }
    },
    {
      "fund_name": "UTI India Consumer Fund Direct Growth",
      "source_url": "https://groww.in/mutual-funds/uti-india-lifestyle-fund-direct-growth",
      "chunk_type": "holdings_information",
      "data": {
        "top_holdings": [
          {
            "stock": "Bharti Airtel Ltd.",
            "percentage": "8.18%"
          },
          {
            "stock": "Maruti Suzuki India Ltd.",
            "percentage": "7.05%"
          },
          {
            "stock": "Mahindra & Mahindra Ltd.",
            "percentage": "5.41%"
          },
          {
            "stock": "Titan Company Ltd.",
            "percentage": "4.59%"
          },
          {
            "stock": "ITC Ltd.",
            "percentage": "4.58%"
          }
        ]
      }
    },
    {
      "fund_name": "UTI Nifty 50 Index Fund Direct Growth",
      "source_url": "https://groww.in/mutual-funds/uti-nifty-fund-direct-growth",
      "chunk_type": "holdings_information",
      "data": {
        "top_holdings": [
          {
            "stock": "HDFC Bank Ltd.",
            "percentage": "12.77%"
          },
          {
            "stock": "Reliance Industries Ltd.",
            "percentage": "8.52%"
          },
          {
            "stock": "ICICI Bank Ltd.",
            "percentage": "8.13%"
          },
          {
            "stock": "Bharti Airtel Ltd.",
            "percentage": "4.74%"
          },
          {
            "stock": "Infosys Ltd.",
            "percentage": "4.52%"
          }
        ]
      }
    },
    {
      "fund_name": "UTI Nifty Next 50 Index Fund Direct Growth",
      "source_url": "https://groww.in/mutual-funds/uti-nifty-next-50-index-fund-direct-growth",
      "chunk_type": "holdings_information",
      "data": {
        "top_holdings": [
          {
            "stock": "Hindustan Aeronautics Ltd.",
            "percentage": "3.81%"
          },
          {
            "stock": "Divi's Laboratories Ltd.",
            "percentage": "3.67%"
          },
          {
            "stock": "Vedanta Ltd.",
            "percentage": "3.59%"
          },
          {
            "stock": "TVS Motor Company Ltd.",
            "percentage": "3.53%"
          },
          {
            "stock": "Cholamandalam Investment and Finance Company Ltd.",
            "percentage": "3.06%"
          }
        ]
      }
    },
    {
      "fund_name": "UTI Infrastructure Fund Direct Growth",
      "source_url": "https://groww.in/mutual-funds/uti-infrastructure-fund-direct-growth",
      "chunk_type": "holdings_information",
      "data": {
        "top_holdings": [
          {
            "stock": "Bharti Airtel Ltd.",
            "percentage": "13.35%"
          },
          {
            "stock": "Larsen & Toubro Ltd.",
            "percentage": "10.33%"
          },
          {
            "stock": "Reliance Industries Ltd.",
            "percentage": "6.97%"
          },
          {
            "stock": "NTPC Ltd.",
            "percentage": "6.08%"
          },
          {
            "stock": "Ultratech Cement Ltd.",
            "percentage": "4.73%"
          }
        ]
      }
    },
    {
      "fund_name": "UTI Innovation Fund Direct Growth",
      "source_url": "https://groww.in/mutual-funds/uti-innovation-fund-direct-growth",
      "chunk_type": "holdings_information",
      "data": {
        "top_holdings": [
          {
            "stock": "Eternal Ltd.",
            "percentage": "8.71%"
          },
          {
            "stock": "Info Edge (India) Ltd.",
            "percentage": "8.54%"
          },
          {
            "stock": "PB Fintech Ltd.",
            "percentage": "7.15%"
          },
          {
            "stock": "Affle 3I Ltd.",
            "percentage": "6.07%"
          },
          {
            "stock": "FSN E-Commerce Ventures Ltd.",
            "percentage": "5.44%"
          }
        ]
      }
    },
    {
      "fund_name": "UTI Multi Cap Fund Direct Growth",
      "source_url": "https://groww.in/mutual-funds/uti-multi-cap-fund-direct-growth",
      "chunk_type": "holdings_information",
      "data": {
        "top_holdings": [
          {
            "stock": "Axis Bank Ltd.",
            "percentage": "3.42%"
          },
          {
            "stock": "Kotak Mahindra Bank Ltd.",
            "percentage": "3.37%"
          },
          {
            "stock": "ICICI Bank Ltd.",
            "percentage": "3.22%"
          },
          {
            "stock": "Bharti Airtel Ltd.",
            "percentage": "2.76%"
          },
          {
            "stock": "Bajaj Finance Ltd.",
            "percentage": "2.60%"
          }
        ]
      }
    },
    {
      "fund_name": "UTI Long Term Advantage Fund Series V Direct Growth",
      "source_url": "https://groww.in/mutual-funds/uti-long-term-advantage-fund-series-v-direct-growth",
      "chunk_type": "holdings_information",
      "data": {
        "top_holdings": [
          {
            "stock": "ICICI Bank Ltd.",
            "percentage": "7.05%"
          },
          {
            "stock": "State Bank of India",
            "percentage": "6.37%"
          },
          {
            "stock": "HDFC Bank Ltd.",
            "percentage": "6.22%"
          },
          {
            "stock": "Axis Bank Ltd.",
            "percentage": "4.37%"
          },
          {
            "stock": "Praj Industries Ltd.",
            "percentage": "4.32%"
          }
        ]
      }
    },
    {
      "fund_name": "UTI Long Term Advantage Fund Series III Direct Growth",
      "source_url": "https://groww.in/mutual-funds/uti-long-term-advantage-fund-series-iii-direct-growth",
      "chunk_type": "holdings_information",
      "data": {
        "top_holdings": [
          {
            "stock": "ICICI Bank Ltd.",
            "percentage": "7.06%"
          },
          {
            "stock": "Tech Mahindra Ltd.",
            "percentage": "6.33%"
          },
          {
            "stock": "HDFC Bank Ltd.",
            "percentage": "6.18%"
          },
          {
            "stock": "State Bank of India",
            "percentage": "5.02%"
          },
          {
            "stock": "Praj Industries Ltd.",
            "percentage": "4.48%"
          }
        ]
      }
    },
    {
      "fund_name": "UTI Gold ETF FoF Direct Growth",
      "source_url": "https://groww.in/mutual-funds/uti-gold-etf-fof-direct-growth",
      "chunk_type": "holdings_information",
      "data": {
        "top_holdings": [
          {
            "stock": "UTI Gold Exchange Traded Fund",
            "percentage": "100.03%"
          }
        ]
      }
    },
    {
      "fund_name": "UTI Liquid Direct Growth",
      "source_url": "https://groww.in/mutual-funds/uti-liquid-cash-plan-direct-growth",
      "chunk_type": "holdings_information",
      "data": {
        "top_holdings": [
          {
            "stock": "Reserve Bank of India",
            "percentage": "3.91%"
          },
          {
            "stock": "Reserve Bank of India",
            "percentage": "3.05%"
          },
          {
            "stock": "HDFC Bank Ltd.",
            "percentage": "2.65%"
          },
          {
            "stock": "Reserve Bank of India",
            "percentage": "2.57%"
          },
          {
            "stock": "ICICI Securities Ltd.",
            "percentage": "2.15%"
          }
        ]
      }
    },
    {
      "fund_name": "UTI Money Market Fund Regular Plan Growth",
      "source_url": "https://groww.in/mutual-funds/uti-money-market-fund-regular-plan-growth",
      "chunk_type": "holdings_information",
      "data": {
        "top_holdings": [
          {
            "stock": "Indian Bank",
            "percentage": "2.42%"
          },
          {
            "stock": "Reserve Bank of India",
            "percentage": "2.41%"
          },
          {
            "stock": "Reserve Bank of India",
            "percentage": "2.41%"
          },
          {
            "stock": "National Bank For Agriculture & Rural Development",
            "percentage": "2.17%"
          },
          {
            "stock": "Axis Bank Ltd.",
            "percentage": "2.17%"
          }
        ]
      }
    },
    {
      "fund_name": "UTI Healthcare Fund Direct IDCW",
      "source_url": "https://groww.in/mutual-funds/uti-pharma-and-healthcare-fund-direct-dividend",
      "chunk_type": "holdings_information",
      "data": {
        "top_holdings": [
          {
            "stock": "Sun Pharmaceutical Industries Ltd.",
            "percentage": "9.77%"
          },
          {
            "stock": "Ajanta Pharma Ltd.",
            "percentage": "6.25%"
          },
          {
            "stock": "Lupin Ltd.",
            "percentage": "5.58%"
          },
          {
            "stock": "Glenmark Pharmaceuticals Ltd.",
            "percentage": "4.12%"
          },
          {
            "stock": "Cipla Ltd.",
            "percentage": "3.74%"
          }
        ]
      }
    },
    {
      "fund_name": "UTI Income Plus Arbitrage Active FoF Direct Growth",
      "source_url": "https://groww.in/mutual-funds/uti-i-come-plus-arbitrage-active-fof-direct-growth",
      "chunk_type": "holdings_information",
      "data": {
        "top_holdings": [
          {
            "stock": "UTI Corporate Bond Fund Direct - Growth",
            "percentage": "59.65%"
          },
          {
            "stock": "UTI Arbitrage Fund Direct-Growth",
            "percentage": "38.26%"
          }
        ]
      }
    },
    {
      "fund_name": "UTI India Consumer Fund Direct IDCW",
      "source_url": "https://groww.in/mutual-funds/uti-india-lifestyle-fund-direct-dividend",
      "chunk_type": "holdings_information",
      "data": {
        "top_holdings": [
          {
            "stock": "Bharti Airtel Ltd.",
            "percentage": "8.18%"
          },
          {
            "stock": "Maruti Suzuki India Ltd.",
            "percentage": "7.05%"
          },
          {
            "stock": "Mahindra & Mahindra Ltd.",
            "percentage": "5.41%"
          },
          {
            "stock": "Titan Company Ltd.",
            "percentage": "4.59%"
          },
          {
            "stock": "ITC Ltd.",
            "percentage": "4.58%"
          }
        ]
      }
    },
    {
      "fund_name": "UTI Large & Mid Cap Fund Direct IDCW",
      "source_url": "https://groww.in/mutual-funds/uti-top-100-fund-direct-dividend",
      "chunk_type": "holdings_information",
      "data": {
        "top_holdings": [
          {
            "stock": "HDFC Bank Ltd.",
            "percentage": "5.69%"
          },
          {
            "stock": "ICICI Bank Ltd.",
            "percentage": "3.63%"
          },
          {
            "stock": "Infosys Ltd.",
            "percentage": "3.42%"
          },
          {
            "stock": "Reliance Industries Ltd.",
            "percentage": "3.14%"
          },
          {
            "stock": "ITC Ltd.",
            "percentage": "2.83%"
          }
        ]
      }
    },
    {
      "fund_name": "UTI Large Cap Fund Direct Growth",
      "source_url": "https://groww.in/mutual-funds/uti-unit-scheme-1986-mastershare-direct-growth",
      "chunk_type": "holdings_information",
      "data": {
        "top_holdings": [
          {
            "stock": "HDFC Bank Ltd.",
            "percentage": "9.14%"
          },
          {
            "stock": "ICICI Bank Ltd.",
            "percentage": "7.00%"
          },
          {
            "stock": "Infosys Ltd.",
            "percentage": "5.61%"
          },
          {
            "stock": "Bharti Airtel Ltd.",
            "percentage": "4.14%"
          },
          {
            "stock": "Kotak Mahindra Bank Ltd.",
            "percentage": "3.94%"
          }
        ]
      }
    },
    {
      "fund_name": "UTI Large Cap Fund Direct IDCW",
      "source_url": "https://groww.in/mutual-funds/uti-unit-scheme-1986-mastershare-direct-dividend",
      "chunk_type": "holdings_information",
      "data": {
        "top_holdings": [
          {
            "stock": "HDFC Bank Ltd.",
            "percentage": "9.14%"
          },
          {
            "stock": "ICICI Bank Ltd.",
            "percentage": "7.00%"
          },
          {
            "stock": "Infosys Ltd.",
            "percentage": "5.61%"
          },
          {
            "stock": "Bharti Airtel Ltd.",
            "percentage": "4.14%"
          },
          {
            "stock": "Kotak Mahindra Bank Ltd.",
            "percentage": "3.94%"
          }
        ]
      }
    },
    {
      "fund_name": "UTI Liquid Cash Plan Direct IDCW Monthly",
      "source_url": "https://groww.in/mutual-funds/uti-liquid-cash-plan-direct-monthly-dividend",
      "chunk_type": "holdings_information",
      "data": {
        "top_holdings": [
          {
            "stock": "Reserve Bank of India",
            "percentage": "3.91%"
          },
          {
            "stock": "Reserve Bank of India",
            "percentage": "3.05%"
          },
          {
            "stock": "HDFC Bank Ltd.",
            "percentage": "2.65%"
          },
          {
            "stock": "Reserve Bank of India",
            "percentage": "2.57%"
          },
          {
            "stock": "ICICI Securities Ltd.",
            "percentage": "2.15%"
          }
        ]
      }
    },
    {
      "fund_name": "UTI Long Duration Fund Direct IDCW Quarterly",
      "source_url": "https://groww.in/mutual-funds/uti-long-duration-fund-direct-idcw-quarterly",
      "chunk_type": "holdings_information",
      "data": {
        "top_holdings": [
          {
            "stock": "GOI",
            "percentage": "78.88%"
          },
          {
            "stock": "GOI",
            "percentage": "10.03%"
          },
          {
            "stock": "GOI",
            "percentage": "1.05%"
          }
        ]
      }
    },
    {
      "fund_name": "UTI Monthly Income Scheme Direct Growth",
      "source_url": "https://groww.in/mutual-funds/uti-monthly-i-come-scheme-direct-growth",
      "chunk_type": "holdings_information",
      "data": {
        "top_holdings": [
          {
            "stock": "Afcons Infrastructure Ltd.",
            "percentage": "9.76%"
          },
          {
            "stock": "Bank Of Baroda",
            "percentage": "9.73%"
          },
          {
            "stock": "Vodafone Idea Ltd.",
            "percentage": "9.62%"
          },
          {
            "stock": "Jamnagar Utilities and Power Pvt. Ltd.",
            "percentage": "8.07%"
          },
          {
            "stock": "GOI",
            "percentage": "7.13%"
          }
        ]
      }
    },
    {
      "fund_name": "UTI Multi Asset Allocation Fund Direct Growth",
      "source_url": "https://groww.in/mutual-funds/uti-wealth-builder-fund-direct-growth",
      "chunk_type": "holdings_information",
      "data": {
        "top_holdings": [
          {
            "stock": "UTI Gold Exchange Traded Fund",
            "percentage": "12.10%"
          },
          {
            "stock": "ITC Ltd.",
            "percentage": "2.75%"
          },
          {
            "stock": "Infosys Ltd.",
            "percentage": "2.36%"
          },
          {
            "stock": "Bharti Airtel Ltd.",
            "percentage": "2.22%"
          },
          {
            "stock": "HDFC Bank Ltd.",
            "percentage": "2.12%"
          }
        ]
      }
    },
    {
      "fund_name": "UTI Multi Cap Fund (Ex) Direct Growth",
      "source_url": "https://groww.in/mutual-funds/uti-multi-cap-fund-%28ex%29-direct-growth",
      "chunk_type": "holdings_information",
      "data": {
        "top_holdings": [
          {
            "stock": "ITC Ltd.",
            "percentage": "8.66%"
          },
          {
            "stock": "ICICI Bank Ltd.",
            "percentage": "8.60%"
          },
          {
            "stock": "Aditya Birla Fashion and Retail Ltd.",
            "percentage": "8.52%"
          },
          {
            "stock": "HDFC Bank Ltd.",
            "percentage": "8.16%"
          },
          {
            "stock": "Infosys Ltd.",
            "percentage": "4.94%"
          }
        ]
      }
    },
    {
      "fund_name": "UTI Nifty 500 Value 50 Index Fund Direct Growth",
      "source_url": "https://groww.in/mutual-funds/uti-nifty-500-value-50-index-fund-direct-growth",
      "chunk_type": "holdings_information",
      "data": {
        "top_holdings": [
          {
            "stock": "Hindalco Industries Ltd.",
            "percentage": "5.40%"
          },
          {
            "stock": "Indian Oil Corporation Ltd.",
            "percentage": "5.39%"
          },
          {
            "stock": "State Bank of India",
            "percentage": "5.24%"
          },
          {
            "stock": "Oil And Natural Gas Corporation Ltd.",
            "percentage": "5.18%"
          },
          {
            "stock": "Vedanta Ltd.",
            "percentage": "5.18%"
          }
        ]
      }
    },
    {
      "fund_name": "UTI Nifty Alpha Low Volatility 30 Index Fund Direct Growth",
      "source_url": "https://groww.in/mutual-funds/uti-nifty-alpha-low-volatility-30-index-fund-direct-growth",
      "chunk_type": "holdings_information",
      "data": {
        "top_holdings": [
          {
            "stock": "Apollo Hospitals Enterprise Ltd.",
            "percentage": "4.41%"
          },
          {
            "stock": "HDFC Bank Ltd.",
            "percentage": "4.33%"
          },
          {
            "stock": "ITC Ltd.",
            "percentage": "4.22%"
          },
          {
            "stock": "ICICI Bank Ltd.",
            "percentage": "4.14%"
          },
          {
            "stock": "Bharti Airtel Ltd.",
            "percentage": "4.11%"
          }
        ]
      }
    },
    {
      "fund_name": "UTI Nifty India Manufacturing Index Fund Direct Growth",
      "source_url": "https://groww.in/mutual-funds/uti-nifty-india-manufacturing-index-fund-direct-growth",
      "chunk_type": "holdings_information",
      "data": {
        "top_holdings": [
          {
            "stock": "Reliance Industries Ltd.",
            "percentage": "5.30%"
          },
          {
            "stock": "Maruti Suzuki India Ltd.",
            "percentage": "4.87%"
          },
          {
            "stock": "Mahindra & Mahindra Ltd.",
            "percentage": "4.83%"
          },
          {
            "stock": "Sun Pharmaceutical Industries Ltd.",
            "percentage": "4.66%"
          },
          {
            "stock": "Tata Steel Ltd.",
            "percentage": "3.95%"
          }
        ]
      }
    }
  ],
  "nav_sip_information": [
    {
      "fund_name": "UTI Large & Mid Cap Fund Direct Growth",
      "source_url": "https://groww.in/mutual-funds/uti-large-mid-cap-fund-direct-growth",
      "chunk_type": "nav_sip_information",
      "data": {
        "nav": "198.78",
        "nav_date": "21-11-2025",
        "min_sip": 500,
        "exit_load": "Exit load of 1% if redeemed less than 1 year"
      }
    },
    {
      "fund_name": "UTI ELSS Tax Saver Fund Direct Growth",
      "source_url": "https://groww.in/mutual-funds/uti-long-term-equity-fund-tax-saving-direct-growth",
      "chunk_type": "nav_sip_information",
      "data": {
        "nav": "295.45",
        "nav_date": "21-11-2025",
        "min_sip": 500,
        "exit_load": "Nil"
      }
    },
    {
      "fund_name": "UTI Gold ETF FoF Direct Growth",
      "source_url": "https://groww.in/mutual-funds/uti-gold-etf-fof-direct-growth",
      "chunk_type": "nav_sip_information",
      "data": {
        "nav": "18.52",
        "nav_date": "21-11-2025",
        "min_sip": 500,
        "exit_load": "Exit load of 1%, if redeemed within 15 days"
      }
    },
    {
      "fund_name": "UTI Transportation and Logistics Fund Direct Growth",
      "source_url": "https://groww.in/mutual-funds/uti-transportation-and-logistics-fund-direct-growth",
      "chunk_type": "nav_sip_information",
      "data": {
        "nav": "156.34",
        "nav_date": "21-11-2025",
        "min_sip": 500,
        "exit_load": "Exit load of 1% if redeemed within 30 days."
      }
    },
    {
      "fund_name": "UTI Healthcare Fund Direct Growth",
      "source_url": "https://groww.in/mutual-funds/uti-pharma-and-healthcare-fund-direct-growth",
      "chunk_type": "nav_sip_information",
      "data": {
        "nav": "167.89",
        "nav_date": "21-11-2025",
        "min_sip": 500,
        "exit_load": "Exit load of 1% if redeemed within 30 days."
      }
    },
    {
      "fund_name": "UTI Small Cap Fund Direct Growth",
      "source_url": "https://groww.in/mutual-funds/uti-small-cap-fund-direct-growth",
      "chunk_type": "nav_sip_information",
      "data": {
        "nav": "234.12",
        "nav_date": "21-11-2025",
        "min_sip": 500,
        "exit_load": "Exit load of 1% if redeemed within one year."
      }
    },
    {
      "fund_name": "UTI Value Fund Direct Growth",
      "source_url": "https://groww.in/mutual-funds/uti-value-fund-direct-growth",
      "chunk_type": "nav_sip_information",
      "data": {
        "nav": "312.56",
        "nav_date": "21-11-2025",
        "min_sip": 500,
        "exit_load": "Exit Load for units in excess of 10% of the investment,1% will be charged for redemption within 1 year."
      }
    },
    {
      "fund_name": "UTI Mid Cap Fund Direct Growth",
      "source_url": "https://groww.in/mutual-funds/uti-mid-cap-fund-direct-growth",
      "chunk_type": "nav_sip_information",
      "data": {
        "nav": "289.67",
        "nav_date": "21-11-2025",
        "min_sip": 500,
        "exit_load": "Exit load of 1% if redeemed less than 1 year"
      }
    },
    {
      "fund_name": "UTI Nifty Next 50 Index Fund Direct Growth",
      "source_url": "https://groww.in/mutual-funds/uti-nifty-next-50-index-fund-direct-growth",
      "chunk_type": "nav_sip_information",
      "data": {
        "nav": "287.23",
        "nav_date": "21-11-2025",
        "min_sip": 500,
        "exit_load": "Nil"
      }
    },
    {
      "fund_name": "UTI Banking and Financial Services Fund Direct Plan Growth",
      "source_url": "https://groww.in/mutual-funds/uti-banking-sector-fund-direct-growth",
      "chunk_type": "nav_sip_information",
      "data": {
        "nav": "456.78",
        "nav_date": "21-11-2025",
        "min_sip": 500,
        "exit_load": "Exit load of 1%, if redeemed within 30 days."
      }
    },
    {
      "fund_name": "UTI Nifty 50 Index Fund Direct Growth",
      "source_url": "https://groww.in/mutual-funds/uti-nifty-fund-direct-growth",
      "chunk_type": "nav_sip_information",
      "data": {
        "nav": "278.45",
        "nav_date": "21-11-2025",
        "min_sip": 500,
        "exit_load": "Nil"
      }
    },
    {
      "fund_name": "UTI Flexi Cap Fund Direct Growth",
      "source_url": "https://groww.in/mutual-funds/uti-equity-fund-direct-growth",
      "chunk_type": "nav_sip_information",
      "data": {
        "nav": "412.89",
        "nav_date": "21-11-2025",
        "min_sip": 500,
        "exit_load": "Exit Load for units in excess of 10% of the investment,1% will be charged for redemption within 1 year."
      }
    },
    {
      "fund_name": "UTI Money Market Fund Regular Plan Growth",
      "source_url": "https://groww.in/mutual-funds/uti-money-market-fund-regular-plan-growth",
      "chunk_type": "nav_sip_information",
      "data": {
        "nav": "103.45",
        "nav_date": "21-11-2025",
        "exit_load": "Nil"
      }
    },
    {
      "fund_name": "UTI Liquid Direct Growth",
      "source_url": "https://groww.in/mutual-funds/uti-liquid-cash-plan-direct-growth",
      "chunk_type": "nav_sip_information",
      "data": {
        "nav": "101.23",
        "nav_date": "21-11-2025",
        "exit_load": "Exit load of 0.0070% if redeemed within 1 day, 0.0065% if redeemed within 2 days, 0.0060% if redeemed within 3 days, 0.0055% if redeemed within 4 days, 0.0050% if redeemed within 5 days, 0.0045% if redeemed within 6 days."
      }
    },
    {
      "fund_name": "UTI MNC Fund Direct Growth",
      "source_url": "https://groww.in/mutual-funds/uti-mnc-fund-direct-growth",
      "chunk_type": "nav_sip_information",
      "data": {
        "nav": "189.56",
        "nav_date": "21-11-2025",
        "min_sip": 500,
        "exit_load": "Exit load of 1% if redeemed less than 1 year"
      }
    },
    {
      "fund_name": "UTI India Consumer Fund Direct Growth",
      "source_url": "https://groww.in/mutual-funds/uti-india-lifestyle-fund-direct-growth",
      "chunk_type": "nav_sip_information",
      "data": {
        "nav": "156.78",
        "nav_date": "21-11-2025",
        "min_sip": 500,
        "exit_load": "Exit load of 1% if redeemed within 30 days."
      }
    },
    {
      "fund_name": "UTI Long Term Advantage Fund Series III Direct Growth",
      "source_url": "https://groww.in/mutual-funds/uti-long-term-advantage-fund-series-iii-direct-growth",
      "chunk_type": "nav_sip_information",
      "data": {
        "nav": "145.34",
        "nav_date": "21-11-2025",
        "exit_load": "Nil"
      }
    },
    {
      "fund_name": "UTI Healthcare Fund Direct IDCW",
      "source_url": "https://groww.in/mutual-funds/uti-pharma-and-healthcare-fund-direct-dividend",
      "chunk_type": "nav_sip_information",
      "data": {
        "nav": "165.42",
        "nav_date": "21-11-2025",
        "min_sip": 500,
        "exit_load": "Exit load of 1% if redeemed within 30 days."
      }
    },
    {
      "fund_name": "UTI Income Plus Arbitrage Active FoF Direct Growth",
      "source_url": "https://groww.in/mutual-funds/uti-i-come-plus-arbitrage-active-fof-direct-growth",
      "chunk_type": "nav_sip_information",
      "data": {
        "nav": "102.56",
        "nav_date": "21-11-2025",
        "min_sip": 500,
        "exit_load": "Nil"
      }
    },
    {
      "fund_name": "UTI India Consumer Fund Direct IDCW",
      "source_url": "https://groww.in/mutual-funds/uti-india-lifestyle-fund-direct-dividend",
      "chunk_type": "nav_sip_information",
      "data": {
        "nav": "154.32",
        "nav_date": "21-11-2025",
        "min_sip": 500,
        "exit_load": "Exit load of 1% if redeemed within 30 days."
      }
    },
    {
      "fund_name": "UTI Infrastructure Fund Direct Growth",
      "source_url": "https://groww.in/mutual-funds/uti-infrastructure-fund-direct-growth",
      "chunk_type": "nav_sip_information",
      "data": {
        "nav": "178.65",
        "nav_date": "21-11-2025",
        "min_sip": 500,
        "exit_load": "Exit load of 1% if redeemed within 30 days."
      }
    },
    {
      "fund_name": "UTI Innovation Fund Direct Growth",
      "source_url": "https://groww.in/mutual-funds/uti-innovation-fund-direct-growth",
      "chunk_type": "nav_sip_information",
      "data": {
        "nav": "189.12",
        "nav_date": "21-11-2025",
        "min_sip": 500,
        "exit_load": "Exit load of 1%, if redeemed within 12 months."
      }
    },
    {
      "fund_name": "UTI Large & Mid Cap Fund Direct IDCW",
      "source_url": "https://groww.in/mutual-funds/uti-top-100-fund-direct-dividend",
      "chunk_type": "nav_sip_information",
      "data": {
        "nav": "196.54",
        "nav_date": "21-11-2025",
        "min_sip": 500,
        "exit_load": "Exit load of 1% if redeemed less than 1 year"
      }
    },
    {
      "fund_name": "UTI Large Cap Fund Direct Growth",
      "source_url": "https://groww.in/mutual-funds/uti-unit-scheme-1986-mastershare-direct-growth",
      "chunk_type": "nav_sip_information",
      "data": {
        "nav": "245.78",
        "nav_date": "21-11-2025",
        "min_sip": 500,
        "exit_load": "Exit Load for units in excess of 10% of the investment,1% will be charged for redemption within 1 year."
      }
    },
    {
      "fund_name": "UTI Large Cap Fund Direct IDCW",
      "source_url": "https://groww.in/mutual-funds/uti-unit-scheme-1986-mastershare-direct-dividend",
      "chunk_type": "nav_sip_information",
      "data": {
        "nav": "243.21",
        "nav_date": "21-11-2025",
        "min_sip": 500,
        "exit_load": "Exit Load for units in excess of 10% of the investment,1% will be charged for redemption within 1 year."
      }
    },
    {
      "fund_name": "UTI Liquid Cash Plan Direct IDCW Monthly",
      "source_url": "https://groww.in/mutual-funds/uti-liquid-cash-plan-direct-monthly-dividend",
      "chunk_type": "nav_sip_information",
      "data": {
        "nav": "100.87",
        "nav_date": "21-11-2025",
        "exit_load": "Exit load of 0.0070% if redeemed within 1 day, 0.0065% if redeemed within 2 days, 0.0060% if redeemed within 3 days, 0.0055% if redeemed within 4 days, 0.0050% if redeemed within 5 days, 0.0045% if redeemed within 6 days."
      }
    },
    {
      "fund_name": "UTI Long Duration Fund Direct IDCW Quarterly",
      "source_url": "https://groww.in/mutual-funds/uti-long-duration-fund-direct-idcw-quarterly",
      "chunk_type": "nav_sip_information",
      "data": {
        "nav": "124.56",
        "nav_date": "21-11-2025",
        "exit_load": "Nil"
      }
    },
    {
      "fund_name": "UTI Long Term Advantage Fund Series V Direct Growth",
      "source_url": "https://groww.in/mutual-funds/uti-long-term-advantage-fund-series-v-direct-growth",
      "chunk_type": "nav_sip_information",
      "data": {
        "nav": "138.92",
        "nav_date": "21-11-2025",
        "min_sip": 500,
        "exit_load": "Nil"
      }
    },
    {
      "fund_name": "UTI Monthly Income Scheme Direct Growth",
      "source_url": "https://groww.in/mutual-funds/uti-monthly-i-come-scheme-direct-growth",
      "chunk_type": "nav_sip_information",
      "data": {
        "nav": "112.34",
        "nav_date": "21-11-2025",
        "exit_load": "Exit load of 1% if redeemed within 1 year"
      }
    },
    {
      "fund_name": "UTI Multi Asset Allocation Fund Direct Growth",
      "source_url": "https://groww.in/mutual-funds/uti-wealth-builder-fund-direct-growth",
      "chunk_type": "nav_sip_information",
      "data": {
        "nav": "167.45",
        "nav_date": "21-11-2025",
        "min_sip": 500,
        "exit_load": "Exit load of 1%, if redeemed within 30 days."
      }
    },
    {
      "fund_name": "UTI Multi Cap Fund (Ex) Direct Growth",
      "source_url": "https://groww.in/mutual-funds/uti-multi-cap-fund-%28ex%29-direct-growth",
      "chunk_type": "nav_sip_information",
      "data": {
        "nav": "198.76",
        "nav_date": "21-11-2025",
        "min_sip": 500,
        "exit_load": "Exit load of 1% if redeemed less than 1 year"
      }
    },
    {
      "fund_name": "UTI Multi Cap Fund Direct Growth",
      "source_url": "https://groww.in/mutual-funds/uti-multi-cap-fund-direct-growth",
      "chunk_type": "nav_sip_information",
      "data": {
        "nav": "201.34",
        "nav_date": "21-11-2025",
        "min_sip": 500,
        "exit_load": "Exit load of 1%, if redeemed within 90 days."
      }
    },
    {
      "fund_name": "UTI Nifty 500 Value 50 Index Fund Direct Growth",
      "source_url": "https://groww.in/mutual-funds/uti-nifty-500-value-50-index-fund-direct-growth",
      "chunk_type": "nav_sip_information",
      "data": {
        "nav": "276.89",
        "nav_date": "21-11-2025",
        "min_sip": 500,
        "exit_load": "Nil"
      }
    },
    {
      "fund_name": "UTI Nifty Alpha Low Volatility 30 Index Fund Direct Growth",
      "source_url": "https://groww.in/mutual-funds/uti-nifty-alpha-low-volatility-30-index-fund-direct-growth",
      "chunk_type": "nav_sip_information",
      "data": {
        "nav": "289.45",
        "nav_date": "21-11-2025",
        "min_sip": 500,
        "exit_load": "Nil"
      }
    },
    {
      "fund_name": "UTI Nifty India Manufacturing Index Fund Direct Growth",
      "source_url": "https://groww.in/mutual-funds/uti-nifty-india-manufacturing-index-fund-direct-growth",
      "chunk_type": "nav_sip_information",
      "data": {
        "nav": "264.12",
        "nav_date": "21-11-2025",
        "min_sip": 500,
        "exit_load": "Nil"
      }
    }
  ]
}